[
    {
        "name": "Intel Core i5-14600",
        "mark": 32325,
        "rank": 434
    },
    {
        "name": "Intel 300",
        "mark": 7264,
        "rank": 1855
    },
    {
        "name": "Intel Core i7-14700K",
        "mark": 52166,
        "rank": 214
    },
    {
        "name": "AMD Ryzen 5 2600X",
        "mark": 13874,
        "rank": 1264
    },
    {
        "name": "Intel Core i5-14600K",
        "mark": 38536,
        "rank": 342
    },
    {
        "name": "virt-10.0",
        "mark": 5323,
        "rank": 2269
    },
    {
        "name": "Hygon C86 52xx series",
        "mark": 4080,
        "rank": 2557
    },
    {
        "name": "Intel Core i7-12700K",
        "mark": 34333,
        "rank": 399
    },
    {
        "name": "AMD FX-9830P",
        "mark": 3299,
        "rank": 2832
    },
    {
        "name": "Intel Core i3-N305",
        "mark": 9577,
        "rank": 1578
    },
    {
        "name": "Intel N50",
        "mark": 2609,
        "rank": 3170
    },
    {
        "name": "Intel Core i5-14500",
        "mark": 31136,
        "rank": 460
    },
    {
        "name": "Intel Core i7-14700",
        "mark": 40879,
        "rank": 313
    },
    {
        "name": "Intel Core i3-14100",
        "mark": 15196,
        "rank": 1169
    },
    {
        "name": "Intel Core 3 N350",
        "mark": 7484,
        "rank": 1819
    },
    {
        "name": "AMD Ryzen 5 2600",
        "mark": 13144,
        "rank": 1319
    },
    {
        "name": "AMD Ryzen 7 2700",
        "mark": 15630,
        "rank": 1145
    },
    {
        "name": "AMD Ryzen 5 1500X",
        "mark": 9074,
        "rank": 1635
    },
    {
        "name": "Intel Pentium Gold 8505",
        "mark": 9111,
        "rank": 1629
    },
    {
        "name": "Intel Core i7-13800H",
        "mark": 26341,
        "rank": 610
    },
    {
        "name": "Intel Core i3-13100",
        "mark": 14071,
        "rank": 1247
    },
    {
        "name": "AMD Ryzen 3 1200",
        "mark": 6267,
        "rank": 2049
    },
    {
        "name": "AMD Z-01",
        "mark": 305,
        "rank": 5225
    },
    {
        "name": "Intel Core 5 120",
        "mark": 21566,
        "rank": 813
    },
    {
        "name": "Intel Core i7-14790F",
        "mark": 41012,
        "rank": 312
    },
    {
        "name": "AMD Athlon 64 3500+",
        "mark": 367,
        "rank": 5130
    },
    {
        "name": "AMD FX-4330",
        "mark": 3146,
        "rank": 2901
    },
    {
        "name": "AMD Ryzen 5 1600X",
        "mark": 13013,
        "rank": 1331
    },
    {
        "name": "C-QuadCore C4600@2.0GHz",
        "mark": 1412,
        "rank": 3987
    },
    {
        "name": "AMD Ryzen 3 3300X",
        "mark": 12594,
        "rank": 1356
    },
    {
        "name": "Intel Core i5-13600",
        "mark": 31492,
        "rank": 449
    },
    {
        "name": "Intel Core i5-3570 @ 3.40GHz",
        "mark": 4931,
        "rank": 2354
    },
    {
        "name": "AMD Phenom II X4 945",
        "mark": 2422,
        "rank": 3280
    },
    {
        "name": "AMD Ryzen 5 1600",
        "mark": 12260,
        "rank": 1377
    },
    {
        "name": "Intel Core i5-12500",
        "mark": 19728,
        "rank": 915
    },
    {
        "name": "AMD Phenom II X4 940",
        "mark": 2363,
        "rank": 3322
    },
    {
        "name": "AMD Ryzen 5 3600",
        "mark": 17682,
        "rank": 1036
    },
    {
        "name": "Intel Core i5-14400F",
        "mark": 25612,
        "rank": 632
    },
    {
        "name": "AMD Ryzen 5 2500X",
        "mark": 9391,
        "rank": 1599
    },
    {
        "name": "AMD FX-7600P",
        "mark": 2557,
        "rank": 3197
    },
    {
        "name": "AMD Ryzen 3 3100",
        "mark": 11528,
        "rank": 1426
    },
    {
        "name": "Intel Core i5-14400",
        "mark": 25236,
        "rank": 643
    },
    {
        "name": "Intel Core i3-N300",
        "mark": 8216,
        "rank": 1717
    },
    {
        "name": "Intel Core i7-13700H",
        "mark": 26114,
        "rank": 617
    },
    {
        "name": "Intel Core i5-1340P",
        "mark": 18565,
        "rank": 971
    },
    {
        "name": "AMD Athlon 240GE",
        "mark": 4561,
        "rank": 2434
    },
    {
        "name": "Intel Core i5-4460 @ 3.20GHz",
        "mark": 4918,
        "rank": 2357
    },
    {
        "name": "AMD Ryzen 3 2200G",
        "mark": 6735,
        "rank": 1955
    },
    {
        "name": "AMD FX-4320",
        "mark": 3168,
        "rank": 2893
    },
    {
        "name": "AMD EPYC 3101 4-Core",
        "mark": 6050,
        "rank": 2094
    },
    {
        "name": "Intel Core i3-12100T",
        "mark": 12447,
        "rank": 1365
    },
    {
        "name": "Snapdragon 835",
        "mark": 2610,
        "rank": 3169
    },
    {
        "name": "Intel Core i5-3570K @ 3.40GHz",
        "mark": 4971,
        "rank": 2348
    },
    {
        "name": "Intel Core i3-12100",
        "mark": 12367,
        "rank": 1372
    },
    {
        "name": "AMD Ryzen 5 5500",
        "mark": 19306,
        "rank": 941
    },
    {
        "name": "AMD Ryzen 3 1300X",
        "mark": 6925,
        "rank": 1921
    },
    {
        "name": "Intel Core i5-1230U",
        "mark": 11034,
        "rank": 1464
    },
    {
        "name": "AMD Ryzen 5 1400",
        "mark": 7735,
        "rank": 1784
    }
]